<?xml version="1.0" encoding="UTF-8" ?>
<!DOCTYPE mapper PUBLIC "-//mybatis.org//DTD Mapper 3.0//EN" "http://mybatis.org/dtd/mybatis-3-mapper.dtd" >
<mapper namespace="com.o2o.dao.pojo.GoodsMapper">
    <resultMap id="BaseResultMap" type="com.o2o.dao.pojo.Goods">
        <!--
          WARNING - @mbggenerated
          This element is automatically generated by MyBatis Generator, do not modify.
        -->
        <id column="id" property="id" jdbcType="INTEGER"/>
        <result column="title" property="title" jdbcType="VARCHAR"/>
        <result column="description" property="description" jdbcType="VARCHAR"/>
        <result column="hot" property="hot" jdbcType="INTEGER"/>
        <result column="price" property="price" jdbcType="REAL"/>
        <result column="location" property="location" jdbcType="VARCHAR"/>
        <result column="images" property="images" jdbcType="VARCHAR"/>
        <result column="gmt_create" property="gmtCreate" jdbcType="TIMESTAMP"/>
        <result column="gmt_modify" property="gmtModify" jdbcType="TIMESTAMP"/>
    </resultMap>
    <sql id="Goods_Where_Clause">
        <!--
          WARNING - @mbggenerated
          This element is automatically generated by MyBatis Generator, do not modify.
        -->
        <where>
            <foreach collection="oredCriteria" item="criteria" separator="or">
                <if test="criteria.valid">
                    <trim prefix="(" suffix=")" prefixOverrides="and">
                        <foreach collection="criteria.criteria" item="criterion">
                            <choose>
                                <when test="criterion.noValue">
                                    and ${criterion.condition}
                                </when>
                                <when test="criterion.singleValue">
                                    and ${criterion.condition} #{criterion.value}
                                </when>
                                <when test="criterion.betweenValue">
                                    and ${criterion.condition} #{criterion.value} and #{criterion.secondValue}
                                </when>
                                <when test="criterion.listValue">
                                    and ${criterion.condition}
                                    <foreach collection="criterion.value" item="listItem" open="(" close=")"
                                             separator=",">
                                        #{listItem}
                                    </foreach>
                                </when>
                            </choose>
                        </foreach>
                    </trim>
                </if>
            </foreach>
        </where>
    </sql>
    <sql id="Update_By_Goods_Where_Clause">
        <!--
          WARNING - @mbggenerated
          This element is automatically generated by MyBatis Generator, do not modify.
        -->
        <where>
            <foreach collection="Goods.oredCriteria" item="criteria" separator="or">
                <if test="criteria.valid">
                    <trim prefix="(" suffix=")" prefixOverrides="and">
                        <foreach collection="criteria.criteria" item="criterion">
                            <choose>
                                <when test="criterion.noValue">
                                    and ${criterion.condition}
                                </when>
                                <when test="criterion.singleValue">
                                    and ${criterion.condition} #{criterion.value}
                                </when>
                                <when test="criterion.betweenValue">
                                    and ${criterion.condition} #{criterion.value} and #{criterion.secondValue}
                                </when>
                                <when test="criterion.listValue">
                                    and ${criterion.condition}
                                    <foreach collection="criterion.value" item="listItem" open="(" close=")"
                                             separator=",">
                                        #{listItem}
                                    </foreach>
                                </when>
                            </choose>
                        </foreach>
                    </trim>
                </if>
            </foreach>
        </where>
    </sql>
    <sql id="Base_Column_List">
        <!--
          WARNING - @mbggenerated
          This element is automatically generated by MyBatis Generator, do not modify.
        -->
        id, title, description, hot, price, location, images, gmt_create, gmt_modify
    </sql>
    <select id="selectByGoods" resultMap="BaseResultMap" parameterType="com.o2o.dao.pojo.Goods">
        <!--
          WARNING - @mbggenerated
          This element is automatically generated by MyBatis Generator, do not modify.
        -->
        select
        <if test="distinct">
            distinct
        </if>
        <include refid="Base_Column_List"/>
        from o_goods
        <if test="_parameter != null">
            <include refid="Goods_Where_Clause"/>
        </if>
        <if test="orderByClause != null">
            order by ${orderByClause}
        </if>
    </select>
    <select id="selectByPrimaryKey" resultMap="BaseResultMap" parameterType="java.lang.Integer">
        <!--
          WARNING - @mbggenerated
          This element is automatically generated by MyBatis Generator, do not modify.
        -->
        select
        <include refid="Base_Column_List"/>
        from o_goods
        where id = #{id,jdbcType=INTEGER}
    </select>
    <delete id="deleteByPrimaryKey" parameterType="java.lang.Integer">
        <!--
          WARNING - @mbggenerated
          This element is automatically generated by MyBatis Generator, do not modify.
        -->
        delete from o_goods
        where id = #{id,jdbcType=INTEGER}
    </delete>
    <delete id="deleteByGoods" parameterType="com.o2o.dao.pojo.Goods">
        <!--
          WARNING - @mbggenerated
          This element is automatically generated by MyBatis Generator, do not modify.
        -->
        delete from o_goods
        <if test="_parameter != null">
            <include refid="Goods_Where_Clause"/>
        </if>
    </delete>
    <insert id="insert" parameterType="com.o2o.dao.pojo.Goods">
        <!--
          WARNING - @mbggenerated
          This element is automatically generated by MyBatis Generator, do not modify.
        -->
        insert into o_goods (title, description,
        hot, price, location,
        images, gmt_create, gmt_modify
        )
        values (#{title,jdbcType=VARCHAR}, #{description,jdbcType=VARCHAR},
        #{hot,jdbcType=INTEGER}, #{price,jdbcType=REAL}, #{location,jdbcType=VARCHAR},
        #{images,jdbcType=VARCHAR}, #{gmtCreate,jdbcType=TIMESTAMP}, #{gmtModify,jdbcType=TIMESTAMP}
        )
    </insert>
    <insert id="insertSelective" parameterType="com.o2o.dao.pojo.Goods">
        <!--
          WARNING - @mbggenerated
          This element is automatically generated by MyBatis Generator, do not modify.
        -->
        insert into o_goods
        <trim prefix="(" suffix=")" suffixOverrides=",">
            <if test="id != null">
                id,
            </if>
            <if test="title != null">
                title,
            </if>
            <if test="description != null">
                description,
            </if>
            <if test="hot != null">
                hot,
            </if>
            <if test="price != null">
                price,
            </if>
            <if test="location != null">
                location,
            </if>
            <if test="images != null">
                images,
            </if>
            <if test="gmtCreate != null">
                gmt_create,
            </if>
            <if test="gmtModify != null">
                gmt_modify,
            </if>
        </trim>
        <trim prefix="values (" suffix=")" suffixOverrides=",">
            <if test="id != null">
                #{id,jdbcType=INTEGER},
            </if>
            <if test="title != null">
                #{title,jdbcType=VARCHAR},
            </if>
            <if test="description != null">
                #{description,jdbcType=VARCHAR},
            </if>
            <if test="hot != null">
                #{hot,jdbcType=INTEGER},
            </if>
            <if test="price != null">
                #{price,jdbcType=REAL},
            </if>
            <if test="location != null">
                #{location,jdbcType=VARCHAR},
            </if>
            <if test="images != null">
                #{images,jdbcType=VARCHAR},
            </if>
            <if test="gmtCreate != null">
                #{gmtCreate,jdbcType=TIMESTAMP},
            </if>
            <if test="gmtModify != null">
                #{gmtModify,jdbcType=TIMESTAMP},
            </if>
        </trim>
    </insert>
    <select id="countByGoods" parameterType="com.o2o.dao.pojo.Goods" resultType="java.lang.Integer">
        <!--
          WARNING - @mbggenerated
          This element is automatically generated by MyBatis Generator, do not modify.
        -->
        select count(*) from o_goods
        <if test="_parameter != null">
            <include refid="Goods_Where_Clause"/>
        </if>
    </select>
    <update id="updateByExampleSelective" parameterType="map">
        <!--
          WARNING - @mbggenerated
          This element is automatically generated by MyBatis Generator, do not modify.
        -->
        update o_goods
        <set>
            <if test="record.id != null">
                id = #{record.id,jdbcType=INTEGER},
            </if>
            <if test="record.title != null">
                title = #{record.title,jdbcType=VARCHAR},
            </if>
            <if test="record.description != null">
                description = #{record.description,jdbcType=VARCHAR},
            </if>
            <if test="record.hot != null">
                hot = #{record.hot,jdbcType=INTEGER},
            </if>
            <if test="record.price != null">
                price = #{record.price,jdbcType=REAL},
            </if>
            <if test="record.location != null">
                location = #{record.location,jdbcType=VARCHAR},
            </if>
            <if test="record.images != null">
                images = #{record.images,jdbcType=VARCHAR},
            </if>
            <if test="record.gmtCreate != null">
                gmt_create = #{record.gmtCreate,jdbcType=TIMESTAMP},
            </if>
            <if test="record.gmtModify != null">
                gmt_modify = #{record.gmtModify,jdbcType=TIMESTAMP},
            </if>
        </set>
        <if test="_parameter != null">
            <include refid="Update_By_Goods_Where_Clause"/>
        </if>
    </update>
    <update id="updateByExample" parameterType="map">
        <!--
          WARNING - @mbggenerated
          This element is automatically generated by MyBatis Generator, do not modify.
        -->
        update o_goods
        set id = #{record.id,jdbcType=INTEGER},
        title = #{record.title,jdbcType=VARCHAR},
        description = #{record.description,jdbcType=VARCHAR},
        hot = #{record.hot,jdbcType=INTEGER},
        price = #{record.price,jdbcType=REAL},
        location = #{record.location,jdbcType=VARCHAR},
        images = #{record.images,jdbcType=VARCHAR},
        gmt_create = #{record.gmtCreate,jdbcType=TIMESTAMP},
        gmt_modify = #{record.gmtModify,jdbcType=TIMESTAMP}
        <if test="_parameter != null">
            <include refid="Update_By_Goods_Where_Clause"/>
        </if>
    </update>
    <update id="updateByPrimaryKeySelective" parameterType="com.o2o.dao.pojo.Goods">
        <!--
          WARNING - @mbggenerated
          This element is automatically generated by MyBatis Generator, do not modify.
        -->
        update o_goods
        <set>
            <if test="title != null">
                title = #{title,jdbcType=VARCHAR},
            </if>
            <if test="description != null">
                description = #{description,jdbcType=VARCHAR},
            </if>
            <if test="hot != null">
                hot = #{hot,jdbcType=INTEGER},
            </if>
            <if test="price != null">
                price = #{price,jdbcType=REAL},
            </if>
            <if test="location != null">
                location = #{location,jdbcType=VARCHAR},
            </if>
            <if test="images != null">
                images = #{images,jdbcType=VARCHAR},
            </if>
            <if test="gmtCreate != null">
                gmt_create = #{gmtCreate,jdbcType=TIMESTAMP},
            </if>
            <if test="gmtModify != null">
                gmt_modify = #{gmtModify,jdbcType=TIMESTAMP},
            </if>
        </set>
        where id = #{id,jdbcType=INTEGER}
    </update>
    <update id="updateByPrimaryKey" parameterType="com.o2o.dao.pojo.Goods">
        <!--
          WARNING - @mbggenerated
          This element is automatically generated by MyBatis Generator, do not modify.
        -->
        update o_goods
        set title = #{title,jdbcType=VARCHAR},
        description = #{description,jdbcType=VARCHAR},
        hot = #{hot,jdbcType=INTEGER},
        price = #{price,jdbcType=REAL},
        location = #{location,jdbcType=VARCHAR},
        images = #{images,jdbcType=VARCHAR},
        gmt_create = #{gmtCreate,jdbcType=TIMESTAMP},
        gmt_modify = #{gmtModify,jdbcType=TIMESTAMP}
        where id = #{id,jdbcType=INTEGER}
    </update>
</mapper>